{"version":1,"resource":"vscode-remote://wsl%2Bubuntu-22.04/home/etaico/test1.txt","entries":[{"id":"QB3I.txt","timestamp":1746707980756},{"id":"HRJL.txt","timestamp":1746711823736},{"id":"7KE4.txt","source":"undoRedo.source","timestamp":1746711837106},{"id":"e6mq.txt","timestamp":1746717306816},{"id":"frk8.txt","source":"undoRedo.source","timestamp":1746717315456},{"id":"ZxDE.txt","timestamp":1747324776780},{"id":"Oz1D.txt","timestamp":1747324799203},{"id":"D8je.txt","timestamp":1747324834193},{"id":"droq.txt","timestamp":1747324886830},{"id":"Ta39.txt","timestamp":1747324958205},{"id":"9YNu.txt","timestamp":1747324969005},{"id":"wrHr.txt","source":"undoRedo.source","timestamp":1747324975114},{"id":"fAbU.txt","timestamp":1747325252424},{"id":"M9AO.txt","timestamp":1747325314054},{"id":"uD7L.txt","timestamp":1747325333144},{"id":"fN56.txt","timestamp":1747325360628},{"id":"6z29.txt","timestamp":1747325852058},{"id":"jVRp.txt","timestamp":1747325965180},{"id":"5I8x.txt","timestamp":1747325982345},{"id":"d8qg.txt","timestamp":1747326018405},{"id":"5lwa.txt","timestamp":1747326029900},{"id":"Jws9.txt","timestamp":1747326049408},{"id":"Itvu.txt","timestamp":1747327836303},{"id":"Xnac.txt","timestamp":1747327872122},{"id":"OOne.txt","timestamp":1747327905029},{"id":"oFJr.txt","timestamp":1747327915285},{"id":"zKyu.txt","timestamp":1747328047326},{"id":"mBx7.txt","timestamp":1747328306510},{"id":"ByfF.txt","timestamp":1747328330420},{"id":"IbPQ.txt","timestamp":1747328351808},{"id":"s5T7.txt","timestamp":1747328509284}]}